bitads_client/__init__.py
bitads_client/codes.py
bitads_client/schemas.py
bitads_client/client/__init__.py
bitads_client/client/base.py
bitads_client/client/impl.py
bitads_client-0.1.4.dist-info/LICENSE
bitads_client-0.1.4.dist-info/METADATA
bitads_client-0.1.4.dist-info/WHEEL
bitads_client-0.1.4.dist-info/top_level.txt
bitads_client-0.1.4.dist-info/RECORD
