Metadata-Version: 2.2
Name: bitads-client
Version: 0.1.4
Summary: Asynchronous Python client for BitAds.ai API
Author-email: YDC <yellowduckcoders.dev@gmail.com>
License: MIT License
Requires-Python: >=3.8
License-File: LICENSE
Requires-Dist: pydantic<3.0,>=2.0
Requires-Dist: aiohttp<4.0,>=3.8
Provides-Extra: dev
Requires-Dist: pytest; extra == "dev"
Requires-Dist: mypy; extra == "dev"
Requires-Dist: black; extra == "dev"
